digitaltwins/__init__.py
digitaltwins/core/__init__.py
digitaltwins/core/dataset.py
digitaltwins/core/deleter.py
digitaltwins/core/downloader.py
digitaltwins/core/uploader.py
digitaltwins/gen3/__init__.py
digitaltwins/gen3/auth.py
digitaltwins/gen3/metadata_convertor.py
digitaltwins/gen3/metadata_exporter.py
digitaltwins/gen3/metadata_uploader.py
digitaltwins/gen3/querier.py
digitaltwins/irods/__init__.py
digitaltwins/irods/irods.py
digitaltwins/resources/version_1_2_3/element_mapping.xlsx
digitaltwins/resources/version_2_0_0/element_mapping.xlsx
digitaltwins/resources/version_2_0_0/sds_dictionary/README.md
digitaltwins/resources/version_2_0_0/sds_dictionary/_definitions.yaml
digitaltwins/resources/version_2_0_0/sds_dictionary/_settings.yaml
digitaltwins/resources/version_2_0_0/sds_dictionary/_terms.yaml
digitaltwins/resources/version_2_0_0/sds_dictionary/aliquot.yaml
digitaltwins/resources/version_2_0_0/sds_dictionary/case.yaml
digitaltwins/resources/version_2_0_0/sds_dictionary/code_description.yaml
digitaltwins/resources/version_2_0_0/sds_dictionary/code_parameter.yaml
digitaltwins/resources/version_2_0_0/sds_dictionary/core_metadata_collection.yaml
digitaltwins/resources/version_2_0_0/sds_dictionary/dataset_description.yaml
digitaltwins/resources/version_2_0_0/sds_dictionary/experiment.yaml
digitaltwins/resources/version_2_0_0/sds_dictionary/experimental_metadata.yaml
digitaltwins/resources/version_2_0_0/sds_dictionary/manifest.yaml
digitaltwins/resources/version_2_0_0/sds_dictionary/performance.yaml
digitaltwins/resources/version_2_0_0/sds_dictionary/program.yaml
digitaltwins/resources/version_2_0_0/sds_dictionary/project.yaml
digitaltwins/resources/version_2_0_0/sds_dictionary/resource.yaml
digitaltwins/resources/version_2_0_0/sds_dictionary/sample.yaml
digitaltwins/resources/version_2_0_0/sds_dictionary/slide.yaml
digitaltwins/resources/version_2_0_0/sds_dictionary/slide_count.yaml
digitaltwins/resources/version_2_0_0/sds_dictionary/slide_image.yaml
digitaltwins-0.3.16.dist-info/LICENSE
digitaltwins-0.3.16.dist-info/METADATA
digitaltwins-0.3.16.dist-info/WHEEL
digitaltwins-0.3.16.dist-info/top_level.txt
digitaltwins-0.3.16.dist-info/RECORD
