Metadata-Version: 2.1
Name: digitaltwins
Version: 0.3.16
Summary: A Python tool for interacting with the 12 Labours DigitalTWINS (Digital Translational Workflows for Integrating Systems) Platform
Home-page: https://github.com/ABI-CTT-Group/digitaltwins-api
Author: Thiranja Prasad Babarenda Gamage, Chinchien Lin, Linkun Gao, Jiali Xu, David Nickerson
License: Apache-2.0
License-File: LICENSE
Requires-Dist: gen3 (~=4.21.0)
Requires-Dist: python-irodsclient (>=1.1.8)
Requires-Dist: pandas
Requires-Dist: xlrd
Requires-Dist: PyYAML
Requires-Dist: openpyxl
Requires-Dist: jsonschema
Requires-Dist: dictionaryutils
